CHANGES.rst
LICENSE
MANIFEST.in
README.rst
package.json
setup.py
armstrong/__init__.py
armstrong.dev.egg-info/PKG-INFO
armstrong.dev.egg-info/SOURCES.txt
armstrong.dev.egg-info/dependency_links.txt
armstrong.dev.egg-info/namespace_packages.txt
armstrong.dev.egg-info/requires.txt
armstrong.dev.egg-info/top_level.txt
armstrong/dev/__init__.py
armstrong/dev/default_settings.py
armstrong/dev/dev_django.py
armstrong/dev/tasks.py
armstrong/dev/tests/__init__.py
armstrong/dev/tests/helpers.py
armstrong/dev/tests/runner.py
armstrong/dev/tests/utils/__init__.py
armstrong/dev/tests/utils/backports.py
armstrong/dev/tests/utils/base.py
armstrong/dev/tests/utils/runner.py
armstrong/dev/tests/utils/users.py