Metadata-Version: 1.1
Name: armstrong.dev
Version: 2.0.0
Summary: Tools needed for development and testing of Armstrong
Home-page: http://github.com/armstrong/armstrong.dev/
Author: Texas Tribune & The Center for Investigative Reporting
Author-email: dev@armstrongcms.org
License: UNKNOWN
Platform: UNKNOWN
Classifier: Development Status :: 5 - Production/Stable
Classifier: Environment :: Console
Classifier: Framework :: Django
Classifier: Intended Audience :: Developers
Classifier: License :: OSI Approved :: Apache Software License
Classifier: Operating System :: OS Independent
Classifier: Programming Language :: Python
Classifier: Topic :: Software Development :: Testing
